{"annualized_return": null, "avg_market_exposure": 5194.98, "avg_trade_size": 213.13, "best_market_pnl": 30417.12, "buy_trade_ratio": 0.9242, "calculation_window_days": 15, "calmar_ratio": 2.1116, "category_diversity_score": 1.1556, "coefficient_of_variation": 0.9734, "combined_risk_score": 0, "curve_volatility": 0.4102, "date": "2026-06-28T00:00:00Z", "date_range_end": "2026-06-28T00:00:00Z", "date_range_start": "2026-06-14T00:00:00Z", "days_active": 0, "dominant_market_id": "0xff1ec56e0e47033727e33deab740896fbf1c6bb8a2b0068efdba3d900c7ba7a2", "dominant_market_pnl": 30417.12, "drawdown_frequency": 0.1333, "equity_curve_pattern": "volatile", "flagged_metrics": "{}", "gain_to_pain_ratio": 1.0263, "last_active": "2026-06-28T23:59:59.999999Z", "losing_trades": 60, "market_concentration_ratio": 0.1114, "markets_traded": 72, "max_drawdown": 908.1968, "max_position_pct": 5.6485, "num_markets_traded": 72, "perfect_timing_flag": false, "perfect_timing_score": 0.5577, "performance_by_category": "[{\"roi\": 8.8349, \"category\": \"Sports\", \"win_rate\": 0.5652, \"total_pnl\": 33045.77, \"total_trades\": 1755, \"losing_trades\": 60, \"total_invested\": 374038.24, \"winning_trades\": 78, \"total_buy_trades\": 1622, \"total_sell_trades\": 133}, {\"roi\": 8.4748, \"category\": \"Other\", \"win_rate\": 0.6602, \"total_pnl\": 29076.71, \"total_trades\": 1569, \"losing_trades\": 35, \"total_invested\": 343097.02, \"winning_trades\": 68, \"total_buy_trades\": 1462, \"total_sell_trades\": 107}, {\"roi\": 8.4748, \"category\": \"Sports / Soccer\", \"win_rate\": 0.6602, \"total_pnl\": 29076.71, \"total_trades\": 1569, \"losing_trades\": 35, \"total_invested\": 343097.02, \"winning_trades\": 68, \"total_buy_trades\": 1462, \"total_sell_trades\": 107}, {\"roi\": 23.7938, \"category\": \"Esports / Counter-Strike\", \"win_rate\": 0.2667, \"total_pnl\": 5928.25, \"total_trades\": 145, \"losing_trades\": 22, \"total_invested\": 24915.08, \"winning_trades\": 8, \"total_buy_trades\": 122, \"total_sell_trades\": 23}, {\"roi\": 9.8683, \"category\": \"Esports\", \"win_rate\": 0.2647, \"total_pnl\": 2915.57, \"total_trades\": 171, \"losing_trades\": 25, \"total_invested\": 29544.72, \"winning_trades\": 9, \"total_buy_trades\": 145, \"total_sell_trades\": 26}, {\"roi\": 75.4386, \"category\": \"Sports / Tennis\", \"win_rate\": 1.0, \"total_pnl\": 1053.5, \"total_trades\": 15, \"losing_trades\": 0, \"total_invested\": 1396.5, \"winning_trades\": 1, \"total_buy_trades\": 15, \"total_sell_trades\": 0}, {\"roi\": -65.0738, \"category\": \"Esports / MOBA / Dota 2\", \"win_rate\": 0.25, \"total_pnl\": -3012.68, \"total_trades\": 26, \"losing_trades\": 3, \"total_invested\": 4629.64, \"winning_trades\": 1, \"total_buy_trades\": 23, \"total_sell_trades\": 3}, {\"roi\": -65.0738, \"category\": \"Esports / MOBA\", \"win_rate\": 0.25, \"total_pnl\": -3012.68, \"total_trades\": 26, \"losing_trades\": 3, \"total_invested\": 4629.64, \"winning_trades\": 1, \"total_buy_trades\": 23, \"total_sell_trades\": 3}]", "performance_trend": "declining", "pnl_last_30day": 0, "position_size_consistency": 0.0266, "position_size_volatility_flag": false, "profit_factor": 1.2754, "proxy_wallet": "0x45721362269008ac5988bec2e5c22ca463af5e86", "recovery_time_avg": 2, "risk_level": "LOW", "roi": 8.8349, "sell_trade_ratio": 0.0758, "sharpe_ratio": 0.2491, "similar_wallets_count": 0, "single_market_dependence_flag": false, "sortino_ratio": 0.4663, "statistical_confidence": 0.9761, "stddev_position_size": 5201.17, "suspicious_timing_trades": 0, "suspicious_win_rate_flag": false, "sybil_risk_flag": false, "sybil_risk_score": 0, "timing_anomaly_flag": false, "timing_hit_rate": 0, "timing_z_score": 1.23, "total_buy_trades": 1622, "total_invested": 374038.24, "total_pnl": 33045.77, "total_sell_trades": 133, "total_timed_trades": 1755, "total_trades": 1755, "trade_size_stdev": 5201.1747, "ulcer_index": 0.3065, "win_rate": 0.5652, "win_rate_last_30day": 0, "win_rate_z_score": -0.04, "winning_trades": 78, "worst_market_pnl": -19021.24, "category_breakdown": [{"roi": 8.8349, "category": "Sports", "win_rate": 0.5652, "total_pnl": 33045.77, "total_trades": 1755, "losing_trades": 60, "total_invested": 374038.24, "winning_trades": 78, "total_buy_trades": 1622, "total_sell_trades": 133}, {"roi": 8.4748, "category": "Other", "win_rate": 0.6602, "total_pnl": 29076.71, "total_trades": 1569, "losing_trades": 35, "total_invested": 343097.02, "winning_trades": 68, "total_buy_trades": 1462, "total_sell_trades": 107}, {"roi": 8.4748, "category": "Sports / Soccer", "win_rate": 0.6602, "total_pnl": 29076.71, "total_trades": 1569, "losing_trades": 35, "total_invested": 343097.02, "winning_trades": 68, "total_buy_trades": 1462, "total_sell_trades": 107}, {"roi": 23.7938, "category": "Esports / Counter-Strike", "win_rate": 0.2667, "total_pnl": 5928.25, "total_trades": 145, "losing_trades": 22, "total_invested": 24915.08, "winning_trades": 8, "total_buy_trades": 122, "total_sell_trades": 23}, {"roi": 9.8683, "category": "Esports", "win_rate": 0.2647, "total_pnl": 2915.57, "total_trades": 171, "losing_trades": 25, "total_invested": 29544.72, "winning_trades": 9, "total_buy_trades": 145, "total_sell_trades": 26}, {"roi": 75.4386, "category": "Sports / Tennis", "win_rate": 1.0, "total_pnl": 1053.5, "total_trades": 15, "losing_trades": 0, "total_invested": 1396.5, "winning_trades": 1, "total_buy_trades": 15, "total_sell_trades": 0}, {"roi": -65.0738, "category": "Esports / MOBA / Dota 2", "win_rate": 0.25, "total_pnl": -3012.68, "total_trades": 26, "losing_trades": 3, "total_invested": 4629.64, "winning_trades": 1, "total_buy_trades": 23, "total_sell_trades": 3}, {"roi": -65.0738, "category": "Esports / MOBA", "win_rate": 0.25, "total_pnl": -3012.68, "total_trades": 26, "losing_trades": 3, "total_invested": 4629.64, "winning_trades": 1, "total_buy_trades": 23, "total_sell_trades": 3}], "baseball_pnl": 0, "baseball_trades": 0, "baseball_invested": 0, "sports_pnl": 63175.98, "sports_trades": 3339, "has_mlb_activity": false, "is_sports_trader": true}