{"annualized_return": null, "avg_market_exposure": 62291.05, "avg_trade_size": 328.05, "best_market_pnl": 194512.19, "buy_trade_ratio": 1, "calculation_window_days": 15, "calmar_ratio": 10.9779, "category_diversity_score": 0, "coefficient_of_variation": 1.0939, "combined_risk_score": 10, "curve_volatility": 17.5093, "date": "2026-06-28T00:00:00Z", "date_range_end": "2026-06-28T00:00:00Z", "date_range_start": "2026-06-14T00:00:00Z", "days_active": 0, "dominant_market_id": "0x7ebb07134794576c154f06fbaa1cc61a5292d58e280ce98207977771c0326c27", "dominant_market_pnl": -196000, "drawdown_frequency": 0.2222, "equity_curve_pattern": "volatile", "flagged_metrics": "{perfect_timing}", "gain_to_pain_ratio": 5.6266, "last_active": "2026-06-22T23:59:59.999999Z", "losing_trades": 2, "market_concentration_ratio": 0.1519, "markets_traded": 17, "max_drawdown": 0.2695, "max_position_pct": 20.1492, "num_markets_traded": 17, "perfect_timing_flag": true, "perfect_timing_score": 0.8462, "performance_by_category": "[{\"roi\": 72.2991, \"category\": \"Sports / Soccer\", \"win_rate\": 0.8824, \"total_pnl\": 765609.48, \"total_trades\": 3228, \"losing_trades\": 2, \"total_invested\": 1058947.82, \"winning_trades\": 15, \"total_buy_trades\": 3228, \"total_sell_trades\": 0}, {\"roi\": 72.2991, \"category\": \"Other\", \"win_rate\": 0.8824, \"total_pnl\": 765609.48, \"total_trades\": 3228, \"losing_trades\": 2, \"total_invested\": 1058947.82, \"winning_trades\": 15, \"total_buy_trades\": 3228, \"total_sell_trades\": 0}, {\"roi\": 72.2991, \"category\": \"Sports\", \"win_rate\": 0.8824, \"total_pnl\": 765609.48, \"total_trades\": 3228, \"losing_trades\": 2, \"total_invested\": 1058947.82, \"winning_trades\": 15, \"total_buy_trades\": 3228, \"total_sell_trades\": 0}]", "performance_trend": "declining", "pnl_last_30day": 0, "position_size_consistency": 0, "position_size_volatility_flag": false, "profit_factor": 3.9185, "proxy_wallet": "0x81da605d7dac06478367ed1bae0593b7791ca109", "recovery_time_avg": 1.5, "risk_level": "LOW", "roi": 72.2991, "sell_trade_ratio": 0, "sharpe_ratio": 0.7017, "similar_wallets_count": 0, "single_market_dependence_flag": false, "sortino_ratio": 2.6516, "statistical_confidence": 0.9824, "stddev_position_size": 77226.09, "suspicious_timing_trades": 0, "suspicious_win_rate_flag": false, "sybil_risk_flag": false, "sybil_risk_score": 0, "timing_anomaly_flag": false, "timing_hit_rate": 0, "timing_z_score": 1.17, "total_buy_trades": 3228, "total_invested": 1058947.82, "total_pnl": 765609.48, "total_sell_trades": 0, "total_timed_trades": 3228, "total_trades": 3228, "trade_size_stdev": 77226.0914, "ulcer_index": 0.1407, "win_rate": 0.8824, "win_rate_last_30day": 0, "win_rate_z_score": 2.62, "winning_trades": 15, "worst_market_pnl": -196000, "category_breakdown": [{"roi": 72.2991, "category": "Sports / Soccer", "win_rate": 0.8824, "total_pnl": 765609.48, "total_trades": 3228, "losing_trades": 2, "total_invested": 1058947.82, "winning_trades": 15, "total_buy_trades": 3228, "total_sell_trades": 0}, {"roi": 72.2991, "category": "Other", "win_rate": 0.8824, "total_pnl": 765609.48, "total_trades": 3228, "losing_trades": 2, "total_invested": 1058947.82, "winning_trades": 15, "total_buy_trades": 3228, "total_sell_trades": 0}, {"roi": 72.2991, "category": "Sports", "win_rate": 0.8824, "total_pnl": 765609.48, "total_trades": 3228, "losing_trades": 2, "total_invested": 1058947.82, "winning_trades": 15, "total_buy_trades": 3228, "total_sell_trades": 0}], "baseball_pnl": 0, "baseball_trades": 0, "baseball_invested": 0, "sports_pnl": 1531218.96, "sports_trades": 6456, "has_mlb_activity": false, "is_sports_trader": true}