{"annualized_return": null, "avg_market_exposure": 15536.63, "avg_trade_size": 604.83, "best_market_pnl": 165218.26, "buy_trade_ratio": 0.9465, "calculation_window_days": 15, "calmar_ratio": 0.3207, "category_diversity_score": 1.923, "coefficient_of_variation": 1.7225, "combined_risk_score": 10, "curve_volatility": 1.1259, "date": "2026-06-28T00:00:00Z", "date_range_end": "2026-06-28T00:00:00Z", "date_range_start": "2026-06-14T00:00:00Z", "days_active": 0, "dominant_market_id": "0xff1ec56e0e47033727e33deab740896fbf1c6bb8a2b0068efdba3d900c7ba7a2", "dominant_market_pnl": 165218.26, "drawdown_frequency": 0.0667, "equity_curve_pattern": "hockey-stick", "flagged_metrics": "{position_size_volatility}", "gain_to_pain_ratio": 0.227, "last_active": "2026-06-28T23:59:59.999999Z", "losing_trades": 91, "market_concentration_ratio": 0.074, "markets_traded": 144, "max_drawdown": 2.2177, "max_position_pct": 6.3647, "num_markets_traded": 144, "perfect_timing_flag": false, "perfect_timing_score": 0.5062, "performance_by_category": "[{\"roi\": 5.7838, \"category\": \"Sports\", \"win_rate\": 0.5108, \"total_pnl\": 129399.37, \"total_trades\": 3699, \"losing_trades\": 91, \"total_invested\": 2237274.3, \"winning_trades\": 95, \"total_buy_trades\": 3501, \"total_sell_trades\": 198}, {\"roi\": 86.3581, \"category\": \"Sports / Cricket\", \"win_rate\": 0.6111, \"total_pnl\": 113612.42, \"total_trades\": 199, \"losing_trades\": 7, \"total_invested\": 131559.59, \"winning_trades\": 11, \"total_buy_trades\": 193, \"total_sell_trades\": 6}, {\"roi\": 108.3333, \"category\": \"Sports / Combat Sports\", \"win_rate\": 1.0, \"total_pnl\": 75120.46, \"total_trades\": 4, \"losing_trades\": 0, \"total_invested\": 69341.96, \"winning_trades\": 1, \"total_buy_trades\": 4, \"total_sell_trades\": 0}, {\"roi\": 0.0, \"category\": \"Sports / Basketball / NBA\", \"win_rate\": 1.0, \"total_pnl\": 20839.25, \"total_trades\": 1, \"losing_trades\": 0, \"total_invested\": 0.0, \"winning_trades\": 2, \"total_buy_trades\": 0, \"total_sell_trades\": 1}, {\"roi\": 0.0, \"category\": \"Sports / Basketball\", \"win_rate\": 1.0, \"total_pnl\": 20839.25, \"total_trades\": 1, \"losing_trades\": 0, \"total_invested\": 0.0, \"winning_trades\": 2, \"total_buy_trades\": 0, \"total_sell_trades\": 1}, {\"roi\": 0.7551, \"category\": \"Other\", \"win_rate\": 0.525, \"total_pnl\": 15903.96, \"total_trades\": 3486, \"losing_trades\": 76, \"total_invested\": 2106078.03, \"winning_trades\": 84, \"total_buy_trades\": 3303, \"total_sell_trades\": 183}, {\"roi\": 0.0, \"category\": \"Esports / Counter-Strike\", \"win_rate\": 1.0, \"total_pnl\": 3800.0, \"total_trades\": 0, \"losing_trades\": 0, \"total_invested\": 0.0, \"winning_trades\": 1, \"total_buy_trades\": 0, \"total_sell_trades\": 0}, {\"roi\": 0.0, \"category\": \"Esports\", \"win_rate\": 1.0, \"total_pnl\": 3800.0, \"total_trades\": 0, \"losing_trades\": 0, \"total_invested\": 0.0, \"winning_trades\": 1, \"total_buy_trades\": 0, \"total_sell_trades\": 0}, {\"roi\": 0.0, \"category\": \"Politics\", \"win_rate\": 1.0, \"total_pnl\": 665.96, \"total_trades\": 0, \"losing_trades\": 0, \"total_invested\": 0.0, \"winning_trades\": 2, \"total_buy_trades\": 0, \"total_sell_trades\": 0}, {\"roi\": 0.0, \"category\": \"Politics / US\", \"win_rate\": 1.0, \"total_pnl\": 622.39, \"total_trades\": 0, \"losing_trades\": 0, \"total_invested\": 0.0, \"winning_trades\": 1, \"total_buy_trades\": 0, \"total_sell_trades\": 0}, {\"roi\": 0.0, \"category\": \"Tech & AI\", \"win_rate\": 1.0, \"total_pnl\": 622.39, \"total_trades\": 0, \"losing_trades\": 0, \"total_invested\": 0.0, \"winning_trades\": 1, \"total_buy_trades\": 0, \"total_sell_trades\": 0}, {\"roi\": 0.0, \"category\": \"Culture & Entertainment\", \"win_rate\": 1.0, \"total_pnl\": 43.56, \"total_trades\": 0, \"losing_trades\": 0, \"total_invested\": 0.0, \"winning_trades\": 1, \"total_buy_trades\": 0, \"total_sell_trades\": 0}, {\"roi\": -66.7718, \"category\": \"Sports / Motorsport\", \"win_rate\": 0.1, \"total_pnl\": -285.34, \"total_trades\": 19, \"losing_trades\": 9, \"total_invested\": 427.34, \"winning_trades\": 1, \"total_buy_trades\": 10, \"total_sell_trades\": 9}, {\"roi\": -66.7718, \"category\": \"Sports / Motorsport / F1\", \"win_rate\": 0.1, \"total_pnl\": -285.34, \"total_trades\": 19, \"losing_trades\": 9, \"total_invested\": 427.34, \"winning_trades\": 1, \"total_buy_trades\": 10, \"total_sell_trades\": 9}, {\"roi\": -4.1105, \"category\": \"Sports / Soccer\", \"win_rate\": 0.513, \"total_pnl\": -83687.42, \"total_trades\": 3476, \"losing_trades\": 75, \"total_invested\": 2035945.41, \"winning_trades\": 79, \"total_buy_trades\": 3294, \"total_sell_trades\": 182}]", "performance_trend": "declining", "pnl_last_30day": 0, "position_size_consistency": 0, "position_size_volatility_flag": true, "profit_factor": 1.1236, "proxy_wallet": "0xe72bb501df5306c75c89383d48a1e81073fbb0a0", "recovery_time_avg": 13, "risk_level": "LOW", "roi": 5.8116, "sell_trade_ratio": 0.0535, "sharpe_ratio": 0.0717, "similar_wallets_count": 0, "single_market_dependence_flag": false, "sortino_ratio": 0.1154, "statistical_confidence": 0.9836, "stddev_position_size": 28974.51, "suspicious_timing_trades": 0, "suspicious_win_rate_flag": false, "sybil_risk_flag": false, "sybil_risk_score": 0, "timing_anomaly_flag": false, "timing_hit_rate": 0, "timing_z_score": 0.95, "total_buy_trades": 3501, "total_invested": 2237274.3, "total_pnl": 130021.76, "total_sell_trades": 198, "total_timed_trades": 3699, "total_trades": 3699, "trade_size_stdev": 28974.5079, "ulcer_index": 1.4745, "win_rate": 0.5134, "win_rate_last_30day": 0, "win_rate_z_score": -1.48, "winning_trades": 96, "worst_market_pnl": -130967.35, "category_breakdown": [{"roi": 5.7838, "category": "Sports", "win_rate": 0.5108, "total_pnl": 129399.37, "total_trades": 3699, "losing_trades": 91, "total_invested": 2237274.3, "winning_trades": 95, "total_buy_trades": 3501, "total_sell_trades": 198}, {"roi": 86.3581, "category": "Sports / Cricket", "win_rate": 0.6111, "total_pnl": 113612.42, "total_trades": 199, "losing_trades": 7, "total_invested": 131559.59, "winning_trades": 11, "total_buy_trades": 193, "total_sell_trades": 6}, {"roi": 108.3333, "category": "Sports / Combat Sports", "win_rate": 1.0, "total_pnl": 75120.46, "total_trades": 4, "losing_trades": 0, "total_invested": 69341.96, "winning_trades": 1, "total_buy_trades": 4, "total_sell_trades": 0}, {"roi": 0.0, "category": "Sports / Basketball / NBA", "win_rate": 1.0, "total_pnl": 20839.25, "total_trades": 1, "losing_trades": 0, "total_invested": 0.0, "winning_trades": 2, "total_buy_trades": 0, "total_sell_trades": 1}, {"roi": 0.0, "category": "Sports / Basketball", "win_rate": 1.0, "total_pnl": 20839.25, "total_trades": 1, "losing_trades": 0, "total_invested": 0.0, "winning_trades": 2, "total_buy_trades": 0, "total_sell_trades": 1}, {"roi": 0.7551, "category": "Other", "win_rate": 0.525, "total_pnl": 15903.96, "total_trades": 3486, "losing_trades": 76, "total_invested": 2106078.03, "winning_trades": 84, "total_buy_trades": 3303, "total_sell_trades": 183}, {"roi": 0.0, "category": "Esports / Counter-Strike", "win_rate": 1.0, "total_pnl": 3800.0, "total_trades": 0, "losing_trades": 0, "total_invested": 0.0, "winning_trades": 1, "total_buy_trades": 0, "total_sell_trades": 0}, {"roi": 0.0, "category": "Esports", "win_rate": 1.0, "total_pnl": 3800.0, "total_trades": 0, "losing_trades": 0, "total_invested": 0.0, "winning_trades": 1, "total_buy_trades": 0, "total_sell_trades": 0}, {"roi": 0.0, "category": "Politics", "win_rate": 1.0, "total_pnl": 665.96, "total_trades": 0, "losing_trades": 0, "total_invested": 0.0, "winning_trades": 2, "total_buy_trades": 0, "total_sell_trades": 0}, {"roi": 0.0, "category": "Politics / US", "win_rate": 1.0, "total_pnl": 622.39, "total_trades": 0, "losing_trades": 0, "total_invested": 0.0, "winning_trades": 1, "total_buy_trades": 0, "total_sell_trades": 0}, {"roi": 0.0, "category": "Tech & AI", "win_rate": 1.0, "total_pnl": 622.39, "total_trades": 0, "losing_trades": 0, "total_invested": 0.0, "winning_trades": 1, "total_buy_trades": 0, "total_sell_trades": 0}, {"roi": 0.0, "category": "Culture & Entertainment", "win_rate": 1.0, "total_pnl": 43.56, "total_trades": 0, "losing_trades": 0, "total_invested": 0.0, "winning_trades": 1, "total_buy_trades": 0, "total_sell_trades": 0}, {"roi": -66.7718, "category": "Sports / Motorsport", "win_rate": 0.1, "total_pnl": -285.34, "total_trades": 19, "losing_trades": 9, "total_invested": 427.34, "winning_trades": 1, "total_buy_trades": 10, "total_sell_trades": 9}, {"roi": -66.7718, "category": "Sports / Motorsport / F1", "win_rate": 0.1, "total_pnl": -285.34, "total_trades": 19, "losing_trades": 9, "total_invested": 427.34, "winning_trades": 1, "total_buy_trades": 10, "total_sell_trades": 9}, {"roi": -4.1105, "category": "Sports / Soccer", "win_rate": 0.513, "total_pnl": -83687.42, "total_trades": 3476, "losing_trades": 75, "total_invested": 2035945.41, "winning_trades": 79, "total_buy_trades": 3294, "total_sell_trades": 182}], "baseball_pnl": 0, "baseball_trades": 0, "baseball_invested": 0, "sports_pnl": 275552.65, "sports_trades": 7418, "has_mlb_activity": false, "is_sports_trader": true}